tempmailorg/__init__.py
tempmailorg/tempmail.py
tempmailorg-0.0.3.dist-info/LICENSE
tempmailorg-0.0.3.dist-info/METADATA
tempmailorg-0.0.3.dist-info/WHEEL
tempmailorg-0.0.3.dist-info/entry_points.txt
tempmailorg-0.0.3.dist-info/top_level.txt
tempmailorg-0.0.3.dist-info/RECORD
