Metadata-Version: 2.1
Name: tempmailorg
Version: 0.0.3
Summary: temp-mail.org unofficial api wrapper
Home-page: https://github.com/yell0w4x/tempmailorg
Author: yell0w4x
License: MIT
Project-URL: Bug Tracker, https://github.com/yell0w4x/tempmailorg/issues
Keywords: temp mail
Classifier: Programming Language :: Python :: 3
Classifier: Operating System :: OS Independent
Requires-Python: >=3.8
License-File: LICENSE
